amitAi/__init__.py
amitAi/perceptron.py
perceptron_pkg_pkamit-0.0.3.dist-info/LICENSE
perceptron_pkg_pkamit-0.0.3.dist-info/METADATA
perceptron_pkg_pkamit-0.0.3.dist-info/WHEEL
perceptron_pkg_pkamit-0.0.3.dist-info/top_level.txt
perceptron_pkg_pkamit-0.0.3.dist-info/RECORD
